rtl/smart_home_controller.v
module smart_home_controller(
    input wire clk,
    input wire reset,

    input wire motion_sensor,
    input wire dark_sensor,
    input wire temp_high,
    input wire door_open,
    input wire manual_override,
    input wire security_mode,

    output reg light,
    output reg fan,
    output reg ac,
    output reg alarm,
    output reg energy_save
);

always @(posedge clk or posedge reset)
begin
    if(reset)
    begin
        light <= 0;
        fan <= 0;
        ac <= 0;
        alarm <= 0;
        energy_save <= 0;
    end
    else
    begin

        // Default values
        light <= 0;
        fan <= 0;
        ac <= 0;
        alarm <= 0;
        energy_save <= 0;

        // Highest Priority: Security Alarm
        if(security_mode && door_open)
        begin
            alarm <= 1;
        end

        // Manual Override
        else if(manual_override)
        begin
            light <= 1;
            fan <= 1;
        end

        // Automatic Lighting
        else if(motion_sensor && dark_sensor)
        begin
            light <= 1;
        end

        // Temperature Control
        if(temp_high)
        begin
            fan <= 1;
            ac <= 1;
        end

        // Energy Saving
        if(!motion_sensor)
        begin
            energy_save <= 1;
        end

    end
end

endmodule

tb/smart_home_tb.v
`timescale 1ns/1ps

module smart_home_tb;

reg clk;
reg reset;

reg motion_sensor;
reg dark_sensor;
reg temp_high;
reg door_open;
reg manual_override;
reg security_mode;

wire light;
wire fan;
wire ac;
wire alarm;
wire energy_save;

smart_home_controller DUT(
    .clk(clk),
    .reset(reset),
    .motion_sensor(motion_sensor),
    .dark_sensor(dark_sensor),
    .temp_high(temp_high),
    .door_open(door_open),
    .manual_override(manual_override),
    .security_mode(security_mode),
    .light(light),
    .fan(fan),
    .ac(ac),
    .alarm(alarm),
    .energy_save(energy_save)
);

// Clock generation
always #5 clk = ~clk;

initial
begin

    $dumpfile("home.vcd");
    $dumpvars(0, smart_home_tb);

    clk = 0;
    reset = 1;

    motion_sensor = 0;
    dark_sensor = 0;
    temp_high = 0;
    door_open = 0;
    manual_override = 0;
    security_mode = 0;

    #20;
    reset = 0;

    // Test 1 : Motion + Dark
    #20;
    motion_sensor = 1;
    dark_sensor = 1;

    #40;

    // Test 2 : Temperature High
    temp_high = 1;

    #40;

    // Test 3 : Security Alarm
    security_mode = 1;
    door_open = 1;

    #40;

    // Test 4 : Manual Override
    security_mode = 0;
    door_open = 0;
    manual_override = 1;

    #40;

    // Test 5 : Energy Saving
    manual_override = 0;
    motion_sensor = 0;
    dark_sensor = 0;
    temp_high = 0;

    #50;

    $finish;

end

endmodule

home.vcd
$date
	Fri Jun 19 20:27:02 2026
$end
$version
	Icarus Verilog
$end
$timescale
	1ps
$end
$scope module smart_home_tb $end
$var wire 1 ! light $end
$var wire 1 " fan $end
$var wire 1 # energy_save $end
$var wire 1 $ alarm $end
$var wire 1 % ac $end
$var reg 1 & clk $end
$var reg 1 ' dark_sensor $end
$var reg 1 ( door_open $end
$var reg 1 ) manual_override $end
$var reg 1 * motion_sensor $end
$var reg 1 + reset $end
$var reg 1 , security_mode $end
$var reg 1 - temp_high $end
$scope module DUT $end
$var wire 1 & clk $end
$var wire 1 ' dark_sensor $end
$var wire 1 ( door_open $end
$var wire 1 ) manual_override $end
$var wire 1 * motion_sensor $end
$var wire 1 + reset $end
$var wire 1 , security_mode $end
$var wire 1 - temp_high $end
$var reg 1 % ac $end
$var reg 1 $ alarm $end
$var reg 1 # energy_save $end
$var reg 1 " fan $end
$var reg 1 ! light $end
$upscope $end
$upscope $end
$enddefinitions $end
#0
$dumpvars
0-
0,
1+
0*
0)
0(
0'
0&
0%
0$
0#
0"
0!
$end
#5000
1&
#10000
0&
#15000
1&
#20000
0&
0+
#25000
1#
1&
#30000
0&
#35000
1#
1&
#40000
0&
1'
1*
#45000
1!
0#
1&
#50000
0&
#55000
1!
1&
#60000
0&
#65000
1!
1&
#70000
0&
#75000
1!
1&
#80000
0&
1-
#85000
1%
1"
1!
1&
#90000
0&
#95000
1%
1"
1!
1&
#100000
0&
#105000
1%
1"
1!
1&
#110000
0&
#115000
1%
1"
1!
1&
#120000
0&
1(
1,
#125000
1$
1%
1"
0!
1&
#130000
0&
#135000
1$
1%
1"
1&
#140000
0&
#145000
1$
1%
1"
1&
#150000
0&
#155000
1$
1%
1"
1&
#160000
0&
1)
0(
0,
#165000
1!
0$
1%
1"
1&
#170000
0&
#175000
1%
1"
1!
1&
#180000
0&
#185000
1%
1"
1!
1&
#190000
0&
#195000
1%
1"
1!
1&
#200000
0&
0-
0'
0*
0)
#205000
1#
0%
0"
0!
1&
#210000
0&
#215000
1#
1&
#220000
0&
#225000
1#
1&
#230000
0&
#235000
1#
1&
#240000
0&
#245000
1#
1&
